chatbot_reliability/__init__.py
chatbot_reliability/asgi.py
chatbot_reliability/settings.py
chatbot_reliability/urls.py
chatbot_reliability/wsgi.py
reliability_app/__init__.py
reliability_app/admin.py
reliability_app/apps.py
reliability_app/models.py
reliability_app/tests.py
reliability_app/views.py
reliability_app/migrations/__init__.py
chatbot_reliability-0.3.dist-info/LICENSE
chatbot_reliability-0.3.dist-info/METADATA
chatbot_reliability-0.3.dist-info/WHEEL
chatbot_reliability-0.3.dist-info/top_level.txt
chatbot_reliability-0.3.dist-info/RECORD
