Metadata-Version: 2.1
Name: chatbot_reliability
Version: 0.3
License-File: LICENSE
Requires-Dist: nltk
Requires-Dist: inflect
Requires-Dist: sentence-transformers
Requires-Dist: scikit-learn
